pyje/__init__.py
pyje/main.py
pyje-0.0.2.dist-info/METADATA
pyje-0.0.2.dist-info/WHEEL
pyje-0.0.2.dist-info/top_level.txt
pyje-0.0.2.dist-info/RECORD
