Metadata-Version: 2.1
Name: pyje
Version: 0.0.2
Summary: Journal Entry with python
Home-page: https://github.com/jamesKim7/pyje
Author: jameskim
Author-email: kibum1991@naver.com
Classifier: Programming Language :: Python :: 3
Classifier: License :: OSI Approved :: MIT License
Classifier: Operating System :: OS Independent
Requires-Python: >=3.6
Requires-Dist: openpyxl
